{"mc":{
	"debuff001":{
		"frameRate":24,
		"labels":[
			{"name":"debuff001","frame":1}
			
			],
		"frames":[
			
			{
			"res":"F4558825",
			"x":0,
			"y":0
			},
			{
			"res":"916A8FD1",
			"x":0,
			"y":0
			},
			{
			"res":"FDE5873C",
			"x":0,
			"y":0
			},
			{
			"res":"90BEDC6",
			"x":0,
			"y":0
			},
			{
			"res":"29FD811B",
			"x":0,
			"y":0
			},
			{
			"res":"A666A1BB",
			"x":0,
			"y":0
			},
			{
			"res":"EFC19330",
			"x":0,
			"y":0
			},
			{
			"res":"50CE3FF9",
			"x":0,
			"y":0
			},
			{
			"res":"C3AC355",
			"x":0,
			"y":0
			},
			{
			"res":"C0C95403",
			"x":0,
			"y":0
			},
			{
			"res":"9B103348",
			"x":0,
			"y":0
			},
			{
			"res":"E8C4BE25",
			"x":0,
			"y":0
			},
			{
			"res":"F6886301",
			"x":0,
			"y":0
			},
			{
			"res":"D1FC7B89",
			"x":0,
			"y":0
			},
			{
			"res":"FE9D82AE",
			"x":0,
			"y":0
			},
			{
			"res":"C8140D6D",
			"x":0,
			"y":0
			}
			]
}},
	"res":{
		"F4558825":{"x":1,"y":1,"w":86,"h":178},
		"916A8FD1":{"x":1,"y":181,"w":86,"h":178},
		"FDE5873C":{"x":89,"y":1,"w":86,"h":178},
		"90BEDC6":{"x":89,"y":181,"w":86,"h":178},
		"29FD811B":{"x":177,"y":1,"w":86,"h":178},
		"A666A1BB":{"x":177,"y":181,"w":86,"h":178},
		"EFC19330":{"x":265,"y":1,"w":86,"h":178},
		"50CE3FF9":{"x":265,"y":181,"w":86,"h":178},
		"C3AC355":{"x":353,"y":1,"w":86,"h":178},
		"C0C95403":{"x":353,"y":181,"w":86,"h":178},
		"9B103348":{"x":441,"y":1,"w":86,"h":178},
		"E8C4BE25":{"x":441,"y":181,"w":86,"h":178},
		"F6886301":{"x":529,"y":1,"w":86,"h":178},
		"D1FC7B89":{"x":529,"y":181,"w":86,"h":178},
		"FE9D82AE":{"x":617,"y":1,"w":86,"h":178},
		"C8140D6D":{"x":617,"y":181,"w":86,"h":178}
	}}